[
    {
        "id": "",
        "name": "brass instruments",
        "order": 1,
        "icon": "",
        "header": "root",
        "frequency": "",
        "partOfSpeech": "",
        "usage": "",
        "region": "",
        "definition": "",
        "examples": [],
        "isEnabled": true,
        "children": [
            {
                "id": "",
                "name": "most common",
                "order": 1,
                "icon": "",
                "header": "group",
                "frequency": "",
                "partOfSpeech": "",
                "usage": "",
                "region": "",
                "definition": "",
                "examples": [],
                "isEnabled": true,
                "children": [
                    {
                        "id": "",
                        "name": "trumpet b1",
                        "order": 1,
                        "icon": "",
                        "header": "branch",
                        "frequency": "",
                        "partOfSpeech": "[c]",
                        "usage": "",
                        "region": "",
                        "definition": "trumpet a musical instrument that you blow into, which consists of a curved metal tube that is wide at the end, and three buttons you press to change the notes",
                        "examples": [],
                        "isEnabled": true,
                        "children": [
                            {
                                "id": "",
                                "name": "",
                                "order": 1,
                                "icon": "",
                                "header": "collocation",
                                "frequency": "",
                                "partOfSpeech": "",
                                "usage": "",
                                "region": "",
                                "definition": "",
                                "examples": [],
                                "isEnabled": true,
                                "children": []
                            }
                        ]
                    },
                    {
                        "id": "",
                        "name": "trombone x",
                        "order": 1,
                        "icon": "",
                        "header": "branch",
                        "frequency": "",
                        "partOfSpeech": "[c]",
                        "usage": "",
                        "region": "",
                        "definition": "trombone a large metal musical instrument that you play by blowing into it and sliding a long tube in and out to change the notes : kèn trôm-bon",
                        "examples": [
                            "the main orchestral brass instruments are the horn, trumpet, trombone, and tuba."
                        ],
                        "isEnabled": true,
                        "children": [
                            {
                                "id": "",
                                "name": "",
                                "order": 1,
                                "icon": "",
                                "header": "collocation",
                                "frequency": "",
                                "partOfSpeech": "",
                                "usage": "",
                                "region": "",
                                "definition": "",
                                "examples": [],
                                "isEnabled": true,
                                "children": []
                            }
                        ]
                    },
                    {
                        "id": "",
                        "name": "horn c2",
                        "order": 1,
                        "icon": "",
                        "header": "branch",
                        "frequency": "",
                        "partOfSpeech": "[c]",
                        "usage": "",
                        "region": "",
                        "definition": "horn a curved musical instrument made of metal, which is narrow at the end you blow down to make a sound, and wider towards the other end : kèn co",
                        "examples": [
                            "blow a horn",
                            "the horn section(the players who play the horn in an orchestra or band)"
                        ],
                        "isEnabled": true,
                        "children": [
                            {
                                "id": "",
                                "name": "",
                                "order": 1,
                                "icon": "",
                                "header": "collocation",
                                "frequency": "",
                                "partOfSpeech": "",
                                "usage": "",
                                "region": "",
                                "definition": "",
                                "examples": [],
                                "isEnabled": true,
                                "children": []
                            }
                        ]
                    }
                ]
            },
            {
                "id": "",
                "name": "parts",
                "order": 1,
                "icon": "",
                "header": "group",
                "frequency": "",
                "partOfSpeech": "",
                "usage": "",
                "region": "",
                "definition": "",
                "examples": [],
                "isEnabled": true,
                "children": [
                    {
                        "id": "",
                        "name": "mouthpiece",
                        "order": 1,
                        "icon": "",
                        "header": "branch",
                        "frequency": "",
                        "partOfSpeech": "[ c ]",
                        "usage": "",
                        "region": "",
                        "definition": "the part of a telephone, musical instrument or other device that goes near or between the lips : miệng kèn",
                        "examples": [
                            "to play the recorder, blow gentlyintothe mouthpiece."
                        ],
                        "isEnabled": true,
                        "children": [
                            {
                                "id": "",
                                "name": "",
                                "order": 1,
                                "icon": "",
                                "header": "collocation",
                                "frequency": "",
                                "partOfSpeech": "",
                                "usage": "",
                                "region": "",
                                "definition": "",
                                "examples": [],
                                "isEnabled": true,
                                "children": []
                            }
                        ]
                    },
                    {
                        "id": "",
                        "name": "mute x",
                        "order": 1,
                        "icon": "",
                        "header": "branch",
                        "frequency": "",
                        "partOfSpeech": "[c]",
                        "usage": "",
                        "region": "",
                        "definition": "mute a button or other device on a musical instrument that can be fixed in order to make it quieter : cái chặn tiếng",
                        "examples": [],
                        "isEnabled": true,
                        "children": [
                            {
                                "id": "",
                                "name": "",
                                "order": 1,
                                "icon": "",
                                "header": "collocation",
                                "frequency": "",
                                "partOfSpeech": "",
                                "usage": "",
                                "region": "",
                                "definition": "",
                                "examples": [],
                                "isEnabled": true,
                                "children": []
                            }
                        ]
                    },
                    {
                        "id": "",
                        "name": "reed x",
                        "order": 1,
                        "icon": "",
                        "header": "branch",
                        "frequency": "",
                        "partOfSpeech": "[ c ]",
                        "usage": "",
                        "region": "",
                        "definition": "reed a thin piece of wood or metal which shakes very quickly to produce sound when a musician blows over it : lưỡi gà",
                        "examples": [],
                        "isEnabled": true,
                        "children": [
                            {
                                "id": "",
                                "name": "",
                                "order": 1,
                                "icon": "",
                                "header": "collocation",
                                "frequency": "",
                                "partOfSpeech": "",
                                "usage": "",
                                "region": "",
                                "definition": "",
                                "examples": [],
                                "isEnabled": true,
                                "children": []
                            }
                        ]
                    }
                ]
            },
            {
                "id": "",
                "name": "less common",
                "order": 1,
                "icon": "",
                "header": "group",
                "frequency": "",
                "partOfSpeech": "",
                "usage": "",
                "region": "",
                "definition": "",
                "examples": [],
                "isEnabled": true,
                "children": [
                    {
                        "id": "",
                        "name": "cornet x",
                        "order": 1,
                        "icon": "",
                        "header": "branch",
                        "frequency": "",
                        "partOfSpeech": "[c]",
                        "usage": "",
                        "region": "",
                        "definition": "cornet a musical instrument made from metal, usually brass , that you play by blowing into it : kèn coóc-nê",
                        "examples": [],
                        "isEnabled": true,
                        "children": [
                            {
                                "id": "",
                                "name": "",
                                "order": 1,
                                "icon": "",
                                "header": "collocation",
                                "frequency": "",
                                "partOfSpeech": "",
                                "usage": "",
                                "region": "",
                                "definition": "",
                                "examples": [],
                                "isEnabled": true,
                                "children": []
                            }
                        ]
                    },
                    {
                        "id": "",
                        "name": "tuba x",
                        "order": 1,
                        "icon": "",
                        "header": "branch",
                        "frequency": "",
                        "partOfSpeech": "[c]",
                        "usage": "",
                        "region": "",
                        "definition": "tuba a brass musical instrument consisting of a long bent metal tube which the player blows into, producing low notes kèn tuba",
                        "examples": [],
                        "isEnabled": true,
                        "children": [
                            {
                                "id": "",
                                "name": "",
                                "order": 1,
                                "icon": "",
                                "header": "collocation",
                                "frequency": "",
                                "partOfSpeech": "",
                                "usage": "",
                                "region": "",
                                "definition": "",
                                "examples": [],
                                "isEnabled": true,
                                "children": []
                            }
                        ]
                    }
                ]
            }
        ]
    }
]