[
    {
        "id": "",
        "name": "pushing and shoving",
        "order": 1,
        "icon": "",
        "header": "root",
        "frequency": "",
        "partOfSpeech": "",
        "usage": "",
        "region": "",
        "definition": "",
        "examples": [],
        "isEnabled": true,
        "children": [
            {
                "id": "",
                "name": "to push sb/sth",
                "order": 1,
                "icon": "",
                "header": "group",
                "frequency": "",
                "partOfSpeech": "",
                "usage": "",
                "region": "",
                "definition": "",
                "examples": [],
                "isEnabled": true,
                "children": [
                    {
                        "id": "",
                        "name": "push a2",
                        "order": 1,
                        "icon": "",
                        "header": "branch",
                        "frequency": "",
                        "partOfSpeech": "[i or t]",
                        "usage": "",
                        "region": "",
                        "definition": "push to make sb/sth move by pressing them with your hands, arms etcopp pull:",
                        "examples": [
                            "it didn’t move, so she pushed harder.",
                            "i promised to push him on the swings for as long as he wanted.",
                            "shoppers pushing their grocery carts",
                            "push sb/sth away/back/aside etc",
                            "she pushed him away.",
                            "maria pushed her hair back from her forehead.",
                            "push sb/sth towards/into etc something",
                            "philip pushed him towards the door.",
                            "push sth open/shut",
                            "i slowly pushed the door open.",
                            "---------------------------------------------------------------------------------------------------------------------",
                            "push[c] b1 the act of moving sb/sth by pressing them with your hands or body:",
                            "jodi had stopped swinging. ‘want a push?’ her dad asked.",
                            "give sb/sth a push",
                            "get on the swing and i'll give you a push.",
                            "if the door’s stuck, just give it a push .",
                            "i gave the door a hard push, but it still wouldn't open.",
                            "at/with the push of a button(= used to emphasize how easy a machine is to use )",
                            "files can be attached to your email at the push of a button."
                        ],
                        "isEnabled": true,
                        "children": [
                            {
                                "id": "",
                                "name": "",
                                "order": 1,
                                "icon": "",
                                "header": "collocation",
                                "frequency": "",
                                "partOfSpeech": "",
                                "usage": "",
                                "region": "",
                                "definition": "",
                                "examples": [],
                                "isEnabled": true,
                                "children": []
                            }
                        ]
                    },
                    {
                        "id": "",
                        "name": "shove x",
                        "order": 1,
                        "icon": "",
                        "header": "branch",
                        "frequency": "",
                        "partOfSpeech": "[t]",
                        "usage": "",
                        "region": "",
                        "definition": "shove informal to push sb/sth, using your hands or shoulders, in a rough or careless way: xô đẩy",
                        "examples": [
                            "he shoved her towards the car.",
                            "pushing and shoving",
                            "the children were all pushing and shoving each other.",
                            "everyone waspushing and shovingto see the prince.",
                            "shove sb/sth against/aside/under etc sth",
                            "one of the soldiers shoved her roughly against the wall.",
                            "tom shoved his suitcase under the bed",
                            "armed police shoved the protestors aside to make way for the president’s car.",
                            "shove[c]",
                            "give sb/sth a shoveto push sb/sth suddenly and strongly to force them to move:",
                            "if the door won’t open just give it a shove.",
                            "‘mind your own business!’ said graham, giving me a shove."
                        ],
                        "isEnabled": true,
                        "children": [
                            {
                                "id": "",
                                "name": "",
                                "order": 1,
                                "icon": "",
                                "header": "collocation",
                                "frequency": "",
                                "partOfSpeech": "",
                                "usage": "",
                                "region": "",
                                "definition": "",
                                "examples": [],
                                "isEnabled": true,
                                "children": []
                            }
                        ]
                    },
                    {
                        "id": "",
                        "name": "hustle x",
                        "order": 1,
                        "icon": "",
                        "header": "branch",
                        "frequency": "",
                        "partOfSpeech": "[t]",
                        "usage": "",
                        "region": "",
                        "definition": "hustle to push sb along roughly in order to make them move forward quickly: xô đẩy",
                        "examples": [
                            "hustle sb out/into etc",
                            "two policemen quickly appeared and hustled him out.",
                            "martin seized her arm and hustled her away",
                            "the two men were hustled into a police van and driven away.",
                            "hustle somebody into/out of/through etc something",
                            "i was hustled out of the building by a couple of security men.",
                            "hustle somebody away",
                            "he was hustled away by police officers."
                        ],
                        "isEnabled": true,
                        "children": [
                            {
                                "id": "",
                                "name": "",
                                "order": 1,
                                "icon": "",
                                "header": "collocation",
                                "frequency": "",
                                "partOfSpeech": "",
                                "usage": "",
                                "region": "",
                                "definition": "",
                                "examples": [],
                                "isEnabled": true,
                                "children": []
                            }
                        ]
                    },
                    {
                        "id": "",
                        "name": "bundle x",
                        "order": 1,
                        "icon": "",
                        "header": "branch",
                        "frequency": "",
                        "partOfSpeech": "[t]",
                        "usage": "",
                        "region": "",
                        "definition": "bundle to quickly push sb/sth into sth such as a car, a bag, or a cupboard, for example because you are in a hurry or you want to hide something: tống",
                        "examples": [
                            "▪ her friends managed to get her out of the pub and bundled her home.",
                            "bundle sb/sth into sth",
                            "▪ he had been bundled into the back of a volkswagen by three masked men.",
                            "▪ i collected up the dirty washing and bundled it into the washing machine."
                        ],
                        "isEnabled": true,
                        "children": [
                            {
                                "id": "",
                                "name": "",
                                "order": 1,
                                "icon": "",
                                "header": "collocation",
                                "frequency": "",
                                "partOfSpeech": "",
                                "usage": "",
                                "region": "",
                                "definition": "",
                                "examples": [],
                                "isEnabled": true,
                                "children": []
                            }
                        ]
                    }
                ]
            },
            {
                "id": "",
                "name": "to push sb/sth with your finger, elbow, or with sth pointed",
                "order": 1,
                "icon": "",
                "header": "group",
                "frequency": "",
                "partOfSpeech": "",
                "usage": "",
                "region": "",
                "definition": "",
                "examples": [],
                "isEnabled": true,
                "children": [
                    {
                        "id": "",
                        "name": "nudge x",
                        "order": 1,
                        "icon": "",
                        "header": "branch",
                        "frequency": "",
                        "partOfSpeech": "[t]",
                        "usage": "",
                        "region": "",
                        "definition": "nudge to gently push someone with your elbow to get their attention, especially when you do not want anyone else to notice: thúc",
                        "examples": [
                            "toby nudged my arm. ‘that’s the guy i told you about,’ he whispered.",
                            "christine nudged me and giggled.",
                            "jill nudged him in the ribs.",
                            "nudge[c]",
                            "mark gave me a nudge and indicated two men who had just walked in.",
                            "hannahgaveme a gentlenudge."
                        ],
                        "isEnabled": true,
                        "children": [
                            {
                                "id": "",
                                "name": "",
                                "order": 1,
                                "icon": "",
                                "header": "collocation",
                                "frequency": "",
                                "partOfSpeech": "",
                                "usage": "",
                                "region": "",
                                "definition": "",
                                "examples": [],
                                "isEnabled": true,
                                "children": []
                            }
                        ]
                    },
                    {
                        "id": "",
                        "name": "poke x",
                        "order": 1,
                        "icon": "",
                        "header": "branch",
                        "frequency": "",
                        "partOfSpeech": "[i or t]",
                        "usage": "",
                        "region": "",
                        "definition": "poke to quickly push your finger or some other pointed object into sb/sth",
                        "examples": [
                            "poke sb/sth with sth",
                            "andy poked the fish with his finger to see if it was still alive.",
                            "poke sb in the eye/arm/ribs etc",
                            "be careful with that umbrella or you’ll poke someone in the eye.",
                            "poke at",
                            "he was poking at the dust with a stick, making little patterns.",
                            "poke[c]",
                            "i gave dad a poke to wake him up."
                        ],
                        "isEnabled": true,
                        "children": [
                            {
                                "id": "",
                                "name": "",
                                "order": 1,
                                "icon": "",
                                "header": "collocation",
                                "frequency": "",
                                "partOfSpeech": "",
                                "usage": "",
                                "region": "",
                                "definition": "",
                                "examples": [],
                                "isEnabled": true,
                                "children": []
                            }
                        ]
                    },
                    {
                        "id": "",
                        "name": "prod x",
                        "order": 1,
                        "icon": "",
                        "header": "branch",
                        "frequency": "",
                        "partOfSpeech": "[i or t]",
                        "usage": "",
                        "region": "",
                        "definition": "prod to gently push sb/sth, using your finger ora pointed object: đâm thọc",
                        "examples": [
                            "sergeant thompson raised his stick and prodded the soldier in the chest.",
                            "they walked around him, prodding and pinching him. prod [countable noun]",
                            "he gave the dog a quick prod with his foot.",
                            "‘don’t go to sleep,’ she said, prodding me in the ribs.",
                            "prod at",
                            "theo prodded at the dead snake."
                        ],
                        "isEnabled": true,
                        "children": [
                            {
                                "id": "",
                                "name": "",
                                "order": 1,
                                "icon": "",
                                "header": "collocation",
                                "frequency": "",
                                "partOfSpeech": "",
                                "usage": "",
                                "region": "",
                                "definition": "",
                                "examples": [],
                                "isEnabled": true,
                                "children": []
                            }
                        ]
                    },
                    {
                        "id": "",
                        "name": "dig sb in the ribs x",
                        "order": 1,
                        "icon": "",
                        "header": "branch",
                        "frequency": "",
                        "partOfSpeech": "[]",
                        "usage": "",
                        "region": "",
                        "definition": "dig sb in the ribs to suddenly push your finger or elbow into sb’s body, to get their attention or tell them sth: thúc",
                        "examples": [
                            "▪ jenny dug me sharply in the ribs and told me to be quiet.",
                            "▪ edward laughed loudly, digging me in the ribs, wanting me to share the joke."
                        ],
                        "isEnabled": true,
                        "children": [
                            {
                                "id": "",
                                "name": "",
                                "order": 1,
                                "icon": "",
                                "header": "collocation",
                                "frequency": "",
                                "partOfSpeech": "",
                                "usage": "",
                                "region": "",
                                "definition": "",
                                "examples": [],
                                "isEnabled": true,
                                "children": []
                            }
                        ]
                    }
                ]
            },
            {
                "id": "",
                "name": "to push sth that has wheels or rolls easily",
                "order": 1,
                "icon": "",
                "header": "group",
                "frequency": "",
                "partOfSpeech": "",
                "usage": "",
                "region": "",
                "definition": "",
                "examples": [],
                "isEnabled": true,
                "children": [
                    {
                        "id": "",
                        "name": "push a2",
                        "order": 1,
                        "icon": "",
                        "header": "branch",
                        "frequency": "",
                        "partOfSpeech": "[t]",
                        "usage": "",
                        "region": "",
                        "definition": "push đẩy",
                        "examples": [
                            "paul held the door open for a woman pushing a trolley of heavy books.",
                            "push sth in/around etc something",
                            "shoppers were pushing their carts around the supermarket.",
                            "the car had run out of gas so they pushed it into a side-street."
                        ],
                        "isEnabled": true,
                        "children": [
                            {
                                "id": "",
                                "name": "",
                                "order": 1,
                                "icon": "",
                                "header": "collocation",
                                "frequency": "",
                                "partOfSpeech": "",
                                "usage": "",
                                "region": "",
                                "definition": "",
                                "examples": [],
                                "isEnabled": true,
                                "children": []
                            }
                        ]
                    },
                    {
                        "id": "",
                        "name": "roll b2",
                        "order": 1,
                        "icon": "",
                        "header": "branch",
                        "frequency": "",
                        "partOfSpeech": "[t]",
                        "usage": "",
                        "region": "",
                        "definition": "rollto push something round or something on wheels so that it moves forward :",
                        "examples": [
                            "they rolled the logs down the hill.",
                            "the car still didn’t start so we tried to roll it off the road.",
                            "roll sth along/in/onto etc sth",
                            "roll the chicken breasts in flour.",
                            "roll sth up/down etc sth",
                            "we had so much fun rolling stones down into the river.",
                            ""
                        ],
                        "isEnabled": true,
                        "children": [
                            {
                                "id": "",
                                "name": "",
                                "order": 1,
                                "icon": "",
                                "header": "collocation",
                                "frequency": "",
                                "partOfSpeech": "",
                                "usage": "",
                                "region": "",
                                "definition": "",
                                "examples": [],
                                "isEnabled": true,
                                "children": []
                            }
                        ]
                    },
                    {
                        "id": "",
                        "name": "wheel x",
                        "order": 1,
                        "icon": "",
                        "header": "branch",
                        "frequency": "",
                        "partOfSpeech": "[t always + adverb/preposition ]",
                        "usage": "",
                        "region": "",
                        "definition": "wheel",
                        "examples": [
                            "a)to push something with wheels, for example a bicycle or a trolley , so that it moves forward, while guiding it with your hands : đẩy, dong bộ,",
                            "rob wheeled his bike round the back of the house.",
                            "kate wheeled her bike into the garage.",
                            "i collected a trolley and wheeled it towards the frozen food section.",
                            "b)to move someone or something that is in or on something that has wheels : đẩy",
                            "two nurses were wheeling him into the operating theatre.",
                            "she hated being wheeled round in a wheelchair."
                        ],
                        "isEnabled": true,
                        "children": [
                            {
                                "id": "",
                                "name": "",
                                "order": 1,
                                "icon": "",
                                "header": "collocation",
                                "frequency": "",
                                "partOfSpeech": "",
                                "usage": "",
                                "region": "",
                                "definition": "",
                                "examples": [],
                                "isEnabled": true,
                                "children": []
                            }
                        ]
                    },
                    {
                        "id": "",
                        "name": "trundle x",
                        "order": 1,
                        "icon": "",
                        "header": "branch",
                        "frequency": "",
                        "partOfSpeech": "[t]",
                        "usage": "",
                        "region": "",
                        "definition": "trundle to push something heavy that has wheels, slowly and with difficulty: đẩy",
                        "examples": [
                            "trundle sth in/along etc",
                            "the porters were trundling barrows loaded with vegetables into the market."
                        ],
                        "isEnabled": true,
                        "children": [
                            {
                                "id": "",
                                "name": "",
                                "order": 1,
                                "icon": "",
                                "header": "collocation",
                                "frequency": "",
                                "partOfSpeech": "",
                                "usage": "",
                                "region": "",
                                "definition": "",
                                "examples": [],
                                "isEnabled": true,
                                "children": []
                            }
                        ]
                    }
                ]
            },
            {
                "id": "",
                "name": "to push people in order to move forward",
                "order": 1,
                "icon": "",
                "header": "group",
                "frequency": "",
                "partOfSpeech": "",
                "usage": "",
                "region": "",
                "definition": "",
                "examples": [],
                "isEnabled": true,
                "children": [
                    {
                        "id": "",
                        "name": "push b1",
                        "order": 1,
                        "icon": "",
                        "header": "branch",
                        "frequency": "",
                        "partOfSpeech": "[i or t]",
                        "usage": "",
                        "region": "",
                        "definition": "push to push people, especially in a crowd, in order to move past them or in order to make them move: đẩy, dồn đẩy",
                        "examples": [
                            "don’t push. everyone will get a turn.",
                            "can you tell the people at the back of the queue to stop pushing!",
                            "push your way through/into etc",
                            "he pushed his way through the crowd.push past",
                            "push (your way) past/through/into etc",
                            "a fat man pushed past me in his rush to leave.",
                            "she pushed her way to the front.",
                            "she pushed past me to the front of the line."
                        ],
                        "isEnabled": true,
                        "children": [
                            {
                                "id": "",
                                "name": "",
                                "order": 1,
                                "icon": "",
                                "header": "collocation",
                                "frequency": "",
                                "partOfSpeech": "",
                                "usage": "",
                                "region": "",
                                "definition": "",
                                "examples": [],
                                "isEnabled": true,
                                "children": []
                            }
                        ]
                    },
                    {
                        "id": "",
                        "name": "shove x",
                        "order": 1,
                        "icon": "",
                        "header": "branch",
                        "frequency": "",
                        "partOfSpeech": "[i or t]",
                        "usage": "",
                        "region": "",
                        "definition": "shove to push people in a rough and careless way with your hands, arms, or shoulders in order to move forward or past people: xô đẩy",
                        "examples": [
                            "▪ the people moved forward towards the food, pushing and shoving to get there first.",
                            "shove your way through/into etc: vượt qua",
                            "▪ peter shoved his way through the dense crowd in search of his son.",
                            "shove past",
                            "▪ robert shoved past the others and made his way to the front of the room."
                        ],
                        "isEnabled": true,
                        "children": [
                            {
                                "id": "",
                                "name": "",
                                "order": 1,
                                "icon": "",
                                "header": "collocation",
                                "frequency": "",
                                "partOfSpeech": "",
                                "usage": "",
                                "region": "",
                                "definition": "",
                                "examples": [],
                                "isEnabled": true,
                                "children": []
                            }
                        ]
                    },
                    {
                        "id": "",
                        "name": "barge x",
                        "order": 1,
                        "icon": "",
                        "header": "branch",
                        "frequency": "",
                        "partOfSpeech": "[i always + adverb/preposition or t]",
                        "usage": "",
                        "region": "",
                        "definition": "barge to move somewhere in a rough careless way, often hitting against things or peoplesyn push: chạy xô",
                        "examples": [
                            "barge your way through/to etc sth",
                            "she barged her way through the shopping crowds.",
                            "barge into",
                            "she just barged into me, without even apologizing.",
                            "barge past",
                            "a woman carrying a large basket barged past me to the front of the line.",
                            "she ran outside, barging past bushes and shrubs."
                        ],
                        "isEnabled": true,
                        "children": [
                            {
                                "id": "",
                                "name": "",
                                "order": 1,
                                "icon": "",
                                "header": "collocation",
                                "frequency": "",
                                "partOfSpeech": "",
                                "usage": "",
                                "region": "",
                                "definition": "",
                                "examples": [],
                                "isEnabled": true,
                                "children": []
                            }
                        ]
                    },
                    {
                        "id": "",
                        "name": "force your way c2",
                        "order": 1,
                        "icon": "",
                        "header": "branch",
                        "frequency": "",
                        "partOfSpeech": "[vp]",
                        "usage": "",
                        "region": "",
                        "definition": "force your way to push hard in order to go somewhere when your way is blocked:",
                        "examples": [
                            "force your way through",
                            "▪ he forced his way through the dense crowd.",
                            "force your way into",
                            "▪ police forced their way into the flat and arrested two men."
                        ],
                        "isEnabled": true,
                        "children": [
                            {
                                "id": "",
                                "name": "",
                                "order": 1,
                                "icon": "",
                                "header": "collocation",
                                "frequency": "",
                                "partOfSpeech": "",
                                "usage": "",
                                "region": "",
                                "definition": "",
                                "examples": [],
                                "isEnabled": true,
                                "children": []
                            }
                        ]
                    },
                    {
                        "id": "",
                        "name": "jostle x",
                        "order": 1,
                        "icon": "",
                        "header": "branch",
                        "frequency": "",
                        "partOfSpeech": "[i or t]",
                        "usage": "",
                        "region": "",
                        "definition": "jostle to push against one person or several people so that you knock them to one side, especially in order to reach a place or get sth before they do: chen lấn, xô đẩy",
                        "examples": [
                            "jostle for",
                            "▪ passengers were jostling each other at the news kiosk for the last remaining copies of the evening paper",
                            "jostle to do sth",
                            "▪ the children moved forward, jostling to get to the front and see the magician."
                        ],
                        "isEnabled": true,
                        "children": [
                            {
                                "id": "",
                                "name": "",
                                "order": 1,
                                "icon": "",
                                "header": "collocation",
                                "frequency": "",
                                "partOfSpeech": "",
                                "usage": "",
                                "region": "",
                                "definition": "",
                                "examples": [],
                                "isEnabled": true,
                                "children": []
                            }
                        ]
                    },
                    {
                        "id": "",
                        "name": "elbow x",
                        "order": 1,
                        "icon": "",
                        "header": "branch",
                        "frequency": "",
                        "partOfSpeech": "[t]",
                        "usage": "",
                        "region": "",
                        "definition": "elbow to push with your elbows in order to move past people:thúc ( bằng khuỷu tay)",
                        "examples": [
                            "elbow your way through/into etc",
                            "▪ she elbowed her way through the crowd.",
                            "elbow sb aside/elbow sb to one side",
                            "▪ craig elbowed me aside roughly.",
                            "▪ elbowing me to one side, he took hold of the microphone."
                        ],
                        "isEnabled": true,
                        "children": [
                            {
                                "id": "",
                                "name": "",
                                "order": 1,
                                "icon": "",
                                "header": "collocation",
                                "frequency": "",
                                "partOfSpeech": "",
                                "usage": "",
                                "region": "",
                                "definition": "",
                                "examples": [],
                                "isEnabled": true,
                                "children": []
                            }
                        ]
                    },
                    {
                        "id": "",
                        "name": "press x",
                        "order": 1,
                        "icon": "",
                        "header": "branch",
                        "frequency": "",
                        "partOfSpeech": "[i]",
                        "usage": "",
                        "region": "",
                        "definition": "press to push in order to move forward with the rest of the crowd:ép",
                        "examples": [
                            "press forward/round etc",
                            "▪ as the race started the crowd pressed forward towards the track.",
                            "▪ the security men tried to hold back crowds of reporters pressing round the president’s car."
                        ],
                        "isEnabled": true,
                        "children": [
                            {
                                "id": "",
                                "name": "",
                                "order": 1,
                                "icon": "",
                                "header": "collocation",
                                "frequency": "",
                                "partOfSpeech": "",
                                "usage": "",
                                "region": "",
                                "definition": "",
                                "examples": [],
                                "isEnabled": true,
                                "children": []
                            }
                        ]
                    }
                ]
            },
            {
                "id": "",
                "name": "not here",
                "order": 1,
                "icon": "",
                "header": "group",
                "frequency": "",
                "partOfSpeech": "",
                "usage": "",
                "region": "",
                "definition": "",
                "examples": [],
                "isEnabled": true,
                "children": [
                    {
                        "id": "",
                        "name": "manhandle x",
                        "order": 1,
                        "icon": "",
                        "header": "branch",
                        "frequency": "",
                        "partOfSpeech": "[t]",
                        "usage": "",
                        "region": "",
                        "definition": "manhandle to move sb who does not want to move or sth that is difficult to move by holding on to them and pushing them roughly: vác, khiêng",
                        "examples": [
                            "manhandle sb/sth into/out/towards etc",
                            "▪ the soldiers were manhandling two men into the yard.",
                            "▪ the gang manhandled the stolen trailer through a gap in the fence.",
                            "man‧han‧dle/ ˈmænhændl /verb[ transitive ]",
                            "1to push or handle someone roughly",
                            "manhandle somebody into/through etc something",
                            "it had ended with tony physically manhandling her out of the house.",
                            "2to move a heavy object using force",
                            "manhandle something into/onto/across etc something",
                            "we lifted it off the truck and manhandled it into the workshop."
                        ],
                        "isEnabled": true,
                        "children": [
                            {
                                "id": "",
                                "name": "",
                                "order": 1,
                                "icon": "",
                                "header": "collocation",
                                "frequency": "",
                                "partOfSpeech": "",
                                "usage": "",
                                "region": "",
                                "definition": "",
                                "examples": [],
                                "isEnabled": true,
                                "children": []
                            }
                        ]
                    },
                    {
                        "id": "",
                        "name": "drive c1",
                        "order": 1,
                        "icon": "",
                        "header": "branch",
                        "frequency": "",
                        "usage": "",
                        "region": "",
                        "definition": "driveverbdrove,drivenforce dồn; xua; lùa;",
                        "examples": [
                            "[ t ] to force someone or something to go somewhere or do something",
                            "_they used dogs to drive the sheep into a pen.",
                            "_by the end of the year, most of the occupying troops had been driven from the city.",
                            "_for the second time in ten years, the government has driven the economy into deep and damaging recession.",
                            "_a post had been driven (= hit hard) into the ground near the tree.",
                            "[ + to infinitive ]in the end, it was his violent behaviour that drove hertoleave home."
                        ],
                        "isEnabled": true,
                        "children": [
                            {
                                "id": "",
                                "name": "",
                                "order": 1,
                                "icon": "",
                                "header": "collocation",
                                "frequency": "",
                                "partOfSpeech": "",
                                "usage": "",
                                "region": "",
                                "definition": "",
                                "examples": [],
                                "isEnabled": true,
                                "children": []
                            }
                        ]
                    },
                    {
                        "id": "",
                        "name": "force c2",
                        "order": 1,
                        "icon": "",
                        "header": "branch",
                        "frequency": "",
                        "partOfSpeech": "[ t ]",
                        "usage": "",
                        "region": "",
                        "definition": "forceverbuse physical powerép buộc;cưỡng ép;bắt buộc",
                        "examples": [
                            "to use physical strength or effort to make something move or open",
                            "_move your leg up gently when you're doing this exercise, but don't force it.",
                            "_if you force the zip, it'll break.",
                            "_she forced her way through the crowds."
                        ],
                        "isEnabled": true,
                        "children": [
                            {
                                "id": "",
                                "name": "",
                                "order": 1,
                                "icon": "",
                                "header": "collocation",
                                "frequency": "",
                                "partOfSpeech": "",
                                "usage": "",
                                "region": "",
                                "definition": "",
                                "examples": [],
                                "isEnabled": true,
                                "children": []
                            }
                        ]
                    }
                ]
            }
        ]
    }
]